{
  "version": 1,
  "serviceConfiguration": {
    "apiName": "nextamplifygen1",
    "serviceName": "AppSync",
    "defaultAuthType": {
      "mode": "API_KEY",
      "expirationTime": 365,
      "apiKeyExpirationDate": "2025-03-21T16:44:18.804Z",
      "keyDescription": ""
    },
    "additionalAuthTypes": [
      {
        "mode": "AMAZON_COGNITO_USER_POOLS",
        "cognitoUserPoolId": "authnextamplifygen145198649"
      },
      {
        "mode": "AWS_IAM"
      }
    ],
    "conflictResolution": {}
  }
}